watchmen_collector_kernel/__init__.py
watchmen_collector_kernel/cache/__init__.py
watchmen_collector_kernel/cache/collector_cache_manger.py
watchmen_collector_kernel/cache/collector_cache_service.py
watchmen_collector_kernel/cache/collector_datasource_cache.py
watchmen_collector_kernel/cache/collector_topic_cache.py
watchmen_collector_kernel/cache/model_config_cache.py
watchmen_collector_kernel/cache/module_config_cache.py
watchmen_collector_kernel/cache/table_config_cache.py
watchmen_collector_kernel/common/__init__.py
watchmen_collector_kernel/common/constants.py
watchmen_collector_kernel/common/exception.py
watchmen_collector_kernel/common/settings.py
watchmen_collector_kernel/model/__init__.py
watchmen_collector_kernel/model/change_data_json.py
watchmen_collector_kernel/model/change_data_json_history.py
watchmen_collector_kernel/model/change_data_record.py
watchmen_collector_kernel/model/change_data_record_history.py
watchmen_collector_kernel/model/collector_model_config.py
watchmen_collector_kernel/model/collector_module_config.py
watchmen_collector_kernel/model/collector_table_config.py
watchmen_collector_kernel/model/competitive_lock.py
watchmen_collector_kernel/model/condition.py
watchmen_collector_kernel/model/scheduled_task.py
watchmen_collector_kernel/model/scheduled_task_history.py
watchmen_collector_kernel/model/status.py
watchmen_collector_kernel/model/trigger_event.py
watchmen_collector_kernel/model/trigger_model.py
watchmen_collector_kernel/model/trigger_module.py
watchmen_collector_kernel/model/trigger_table.py
watchmen_collector_kernel/service/__init__.py
watchmen_collector_kernel/service/criteria_builder.py
watchmen_collector_kernel/service/data_capture.py
watchmen_collector_kernel/service/extract_source.py
watchmen_collector_kernel/service/extract_spi.py
watchmen_collector_kernel/service/extract_utils.py
watchmen_collector_kernel/service/lock_helper.py
watchmen_collector_kernel/service/model_config_service.py
watchmen_collector_kernel-18.0.1.dist-info/METADATA
watchmen_collector_kernel-18.0.1.dist-info/WHEEL
watchmen_collector_kernel-18.0.1.dist-info/licenses/LICENSE
watchmen_collector_kernel-18.0.1.dist-info/RECORD
